MANIFEST.in
NEWS.rst
README.rst
setup.py
src/handcrank/__init__.py
src/handcrank/dirchange.py
src/handcrank/directives.py
src/handcrank/generator.py
src/handcrank/report.py
src/handcrank/roles.py
src/handcrank/runner.py
src/handcrank/version.py
src/handcrank.egg-info/PKG-INFO
src/handcrank.egg-info/SOURCES.txt
src/handcrank.egg-info/dependency_links.txt
src/handcrank.egg-info/entry_points.txt
src/handcrank.egg-info/not-zip-safe
src/handcrank.egg-info/requires.txt
src/handcrank.egg-info/top_level.txt
src/handcrank/skeleton/config.cfg
src/handcrank/skeleton/docs/getstarted.rst
src/handcrank/skeleton/template/index.html
src/handcrank/skeleton/template/css/main.less
src/handcrank/skeleton/template/css/pygments.less
src/handcrank/skeleton/template/css/typography.less
src/handcrank/skeleton/template/img/clear-label.png
src/handcrank/skeleton/template/img/drawer.png
src/handcrank/skeleton/template/img/handle.png
src/handcrank/skeleton/template/img/little-crank.png
src/handcrank/skeleton/template/img/new-site-example.png
src/handcrank/skeleton/template/img/pull-folder.png
src/handcrank/skeleton/template/img/site-with-whats-next.png
src/handcrank/skeleton/template/img/very-top-background.png
src/handcrank/skeleton/template/img/folders/closed/lower_left.png
src/handcrank/skeleton/template/img/folders/closed/lower_middle.png
src/handcrank/skeleton/template/img/folders/closed/lower_right.png
src/handcrank/skeleton/template/img/folders/closed/upper_left.png
src/handcrank/skeleton/template/img/folders/closed/upper_left_cap.png
src/handcrank/skeleton/template/img/folders/closed/upper_middle.png
src/handcrank/skeleton/template/img/folders/closed/upper_right.png
src/handcrank/skeleton/template/img/folders/closed/upper_right_cap.png
src/handcrank/skeleton/template/img/folders/open/lower_left.png
src/handcrank/skeleton/template/img/folders/open/lower_middle.png
src/handcrank/skeleton/template/img/folders/open/lower_right.png
src/handcrank/skeleton/template/img/folders/open/upper_left.png
src/handcrank/skeleton/template/img/folders/open/upper_left_cap.png
src/handcrank/skeleton/template/img/folders/open/upper_middle.png
src/handcrank/skeleton/template/img/folders/open/upper_right.png
