Metadata-Version: 1.0
Name: handcrank
Version: 0.1
Summary: A very simple static site generator using reStructuredText
Home-page: http://github.com/robmadole/handcrank
Author: Rob Madole
Author-email: robmadole@gmail.com
License: BSD
Keywords: rst restructuredtext site generator
Platform: UNKNOWN
